shiny_sortable/__init__.py
shiny_sortable/shiny_sortable.py
shiny_sortable-0.1.4.dist-info/LICENSE
shiny_sortable-0.1.4.dist-info/METADATA
shiny_sortable-0.1.4.dist-info/WHEEL
shiny_sortable-0.1.4.dist-info/top_level.txt
shiny_sortable-0.1.4.dist-info/RECORD
