Metadata-Version: 2.1
Name: shiny_sortable
Version: 0.1.4
Summary: A Python library to add sortable functionality to Shiny UI elements
Author-email: Dianyi Yang <kv9898@rubuky.com>
Project-URL: Homepage, https://github.com/kv9898/shiny_sortable
Project-URL: Issues, https://github.com/kv9898/shiny_sortable/issues
Classifier: Programming Language :: Python :: 3
Classifier: License :: OSI Approved :: MIT License
Classifier: Operating System :: OS Independent
Requires-Python: >=3.9
License-File: LICENSE
Requires-Dist: shiny
Requires-Dist: htmltools
